{
	"objects": [
		{
			"id": 0,
			"type": 1,
			"position": {
				"x": 22.11566827278452,
				"y": 25.631178148026088,
				"z": 32.79316500102463
			},
			"orientation": {
				"x": 96.78375405472485,
				"y": 120.69810360851552,
				"z": 283.18790272288226
			},
			"linear_velocity": {
				"x": 0.0,
				"y": 0.0,
				"z": 0.0
			},
			"angular_velocity": {
				"x": 0.0,
				"y": 0.0,
				"z": 0.0
			},
			"linear_acceleration": {
				"x": 0.0,
				"y": 0.0,
				"z": 0.0
			},
			"angular_acceleration": {
				"x": 0.0,
				"y": 0.0,
				"z": 0.0
			}
		},
		{
			"id": 1,
			"type": 0,
			"position": {
				"x": 14.829487652469288,
				"y": 27.652754106896946,
				"z": 27.982109360847097
			},
			"orientation": {
				"x": 206.2111905708827,
				"y": 302.6532297468123,
				"z": 317.3712303679165
			},
			"linear_velocity": {
				"x": 0.0,
				"y": 0.0,
				"z": 0.0
			},
			"angular_velocity": {
				"x": 0.0,
				"y": 0.0,
				"z": 0.0
			},
			"linear_acceleration": {
				"x": 0.0,
				"y": 0.0,
				"z": 0.0
			},
			"angular_acceleration": {
				"x": 0.0,
				"y": 0.0,
				"z": 0.0
			}
		},
		{
			"id": 2,
			"type": 0,
			"position": {
				"x": 16.88619260644565,
				"y": 20.730664198911235,
				"z": 14.24790782850468
			},
			"orientation": {
				"x": 365.5716433175439,
				"y": 216.28776539059575,
				"z": 24.72954355891577
			},
			"linear_velocity": {
				"x": 0.0,
				"y": 0.0,
				"z": 0.0
			},
			"angular_velocity": {
				"x": 0.0,
				"y": 0.0,
				"z": 0.0
			},
			"linear_acceleration": {
				"x": 0.0,
				"y": 0.0,
				"z": 0.0
			},
			"angular_acceleration": {
				"x": 0.0,
				"y": 0.0,
				"z": 0.0
			}
		},
		{
			"id": 3,
			"type": 0,
			"position": {
				"x": 24.34898335408284,
				"y": 17.823566370260146,
				"z": 11.952951945620985
			},
			"orientation": {
				"x": 240.86684814208573,
				"y": 257.3425409561568,
				"z": 114.87453380590738
			},
			"linear_velocity": {
				"x": 0.0,
				"y": 0.0,
				"z": 0.0
			},
			"angular_velocity": {
				"x": 0.0,
				"y": 0.0,
				"z": 0.0
			},
			"linear_acceleration": {
				"x": 0.0,
				"y": 0.0,
				"z": 0.0
			},
			"angular_acceleration": {
				"x": 0.0,
				"y": 0.0,
				"z": 0.0
			}
		},
		{
			"id": 4,
			"type": 1,
			"position": {
				"x": 27.11085220281024,
				"y": 18.224294081037073,
				"z": 22.17036443413521
			},
			"orientation": {
				"x": 241.73549803993936,
				"y": 269.7237283345606,
				"z": 245.10847928365342
			},
			"linear_velocity": {
				"x": 0.0,
				"y": 0.0,
				"z": 0.0
			},
			"angular_velocity": {
				"x": 0.0,
				"y": 0.0,
				"z": 0.0
			},
			"linear_acceleration": {
				"x": 0.0,
				"y": 0.0,
				"z": 0.0
			},
			"angular_acceleration": {
				"x": 0.0,
				"y": 0.0,
				"z": 0.0
			}
		},
		{
			"id": 5,
			"type": 2,
			"position": {
				"x": 19.121192471953805,
				"y": 22.988276779438433,
				"z": 23.904598838503656
			},
			"orientation": {
				"x": 351.48487862150614,
				"y": 133.88711780165977,
				"z": 241.3096303815514
			},
			"linear_velocity": {
				"x": 0.0,
				"y": 0.0,
				"z": 0.0
			},
			"angular_velocity": {
				"x": 0.0,
				"y": 0.0,
				"z": 0.0
			},
			"linear_acceleration": {
				"x": 0.0,
				"y": 0.0,
				"z": 0.0
			},
			"angular_acceleration": {
				"x": 0.0,
				"y": 0.0,
				"z": 0.0
			}
		},
		{
			"id": 6,
			"type": 1,
			"position": {
				"x": 12.208363359103236,
				"y": 25.02448213654413,
				"z": 16.46928782753985
			},
			"orientation": {
				"x": 365.0085949958195,
				"y": 216.23097800656507,
				"z": 289.5440403651065
			},
			"linear_velocity": {
				"x": 0.0,
				"y": 0.0,
				"z": 0.0
			},
			"angular_velocity": {
				"x": 0.0,
				"y": 0.0,
				"z": 0.0
			},
			"linear_acceleration": {
				"x": 0.0,
				"y": 0.0,
				"z": 0.0
			},
			"angular_acceleration": {
				"x": 0.0,
				"y": 0.0,
				"z": 0.0
			}
		},
		{
			"id": 7,
			"type": 1,
			"position": {
				"x": 19.361790291204944,
				"y": 24.73987482954578,
				"z": 26.78252403621104
			},
			"orientation": {
				"x": 238.81349380362792,
				"y": 305.4457830864028,
				"z": 335.3645076833496
			},
			"linear_velocity": {
				"x": 0.0,
				"y": 0.0,
				"z": 0.0
			},
			"angular_velocity": {
				"x": 0.0,
				"y": 0.0,
				"z": 0.0
			},
			"linear_acceleration": {
				"x": 0.0,
				"y": 0.0,
				"z": 0.0
			},
			"angular_acceleration": {
				"x": 0.0,
				"y": 0.0,
				"z": 0.0
			}
		},
		{
			"id": 8,
			"type": 2,
			"position": {
				"x": 22.336896403846353,
				"y": 26.81884988813943,
				"z": 16.143521049979537
			},
			"orientation": {
				"x": 253.2129250384423,
				"y": 136.09990971697337,
				"z": 294.58113258473617
			},
			"linear_velocity": {
				"x": 0.0,
				"y": 0.0,
				"z": 0.0
			},
			"angular_velocity": {
				"x": 0.0,
				"y": 0.0,
				"z": 0.0
			},
			"linear_acceleration": {
				"x": 0.0,
				"y": 0.0,
				"z": 0.0
			},
			"angular_acceleration": {
				"x": 0.0,
				"y": 0.0,
				"z": 0.0
			}
		},
		{
			"id": 9,
			"type": 1,
			"position": {
				"x": 8.683858628175944,
				"y": 17.796129358742004,
				"z": 23.349516535904634
			},
			"orientation": {
				"x": 283.4194403724773,
				"y": 253.4101283899534,
				"z": 370.286518775958
			},
			"linear_velocity": {
				"x": 0.0,
				"y": 0.0,
				"z": 0.0
			},
			"angular_velocity": {
				"x": 0.0,
				"y": 0.0,
				"z": 0.0
			},
			"linear_acceleration": {
				"x": 0.0,
				"y": 0.0,
				"z": 0.0
			},
			"angular_acceleration": {
				"x": 0.0,
				"y": 0.0,
				"z": 0.0
			}
		}
	],
	"timestamp": 39779
}