{
	"objects": [
		{
			"id": 0,
			"type": 1,
			"position": {
				"x": 12.185139077437254,
				"y": 15.306887265833142,
				"z": 22.393703027713048
			},
			"orientation": {
				"x": 87.24832959573783,
				"y": 111.13829701935498,
				"z": 273.2231951695331
			},
			"linear_velocity": {
				"x": 0.0,
				"y": 0.0,
				"z": 0.0
			},
			"angular_velocity": {
				"x": 0.0,
				"y": 0.0,
				"z": 0.0
			},
			"linear_acceleration": {
				"x": 0.0,
				"y": 0.0,
				"z": 0.0
			},
			"angular_acceleration": {
				"x": 0.0,
				"y": 0.0,
				"z": 0.0
			}
		},
		{
			"id": 1,
			"type": 0,
			"position": {
				"x": 4.15572464621998,
				"y": 19.556512868388143,
				"z": 18.514286480944907
			},
			"orientation": {
				"x": 197.6456852115178,
				"y": 297.04262070244584,
				"z": 309.0802722860478
			},
			"linear_velocity": {
				"x": 0.0,
				"y": 0.0,
				"z": 0.0
			},
			"angular_velocity": {
				"x": 0.0,
				"y": 0.0,
				"z": 0.0
			},
			"linear_acceleration": {
				"x": 0.0,
				"y": 0.0,
				"z": 0.0
			},
			"angular_acceleration": {
				"x": 0.0,
				"y": 0.0,
				"z": 0.0
			}
		},
		{
			"id": 2,
			"type": 0,
			"position": {
				"x": 6.254733954820535,
				"y": 12.104151136808902,
				"z": 3.864116292457525
			},
			"orientation": {
				"x": 358.6972111457547,
				"y": 206.8523036456823,
				"z": 16.068208106725603
			},
			"linear_velocity": {
				"x": 0.0,
				"y": 0.0,
				"z": 0.0
			},
			"angular_velocity": {
				"x": 0.0,
				"y": 0.0,
				"z": 0.0
			},
			"linear_acceleration": {
				"x": 0.0,
				"y": 0.0,
				"z": 0.0
			},
			"angular_acceleration": {
				"x": 0.0,
				"y": 0.0,
				"z": 0.0
			}
		},
		{
			"id": 3,
			"type": 0,
			"position": {
				"x": 14.36660545635315,
				"y": 8.11067641815949,
				"z": 2.77534025365388
			},
			"orientation": {
				"x": 234.59450063825338,
				"y": 245.49412735566563,
				"z": 106.19071895512283
			},
			"linear_velocity": {
				"x": 0.0,
				"y": 0.0,
				"z": 0.0
			},
			"angular_velocity": {
				"x": 0.0,
				"y": 0.0,
				"z": 0.0
			},
			"linear_acceleration": {
				"x": 0.0,
				"y": 0.0,
				"z": 0.0
			},
			"angular_acceleration": {
				"x": 0.0,
				"y": 0.0,
				"z": 0.0
			}
		},
		{
			"id": 4,
			"type": 1,
			"position": {
				"x": 18.28959521673844,
				"y": 10.048329994922774,
				"z": 13.94561233271956
			},
			"orientation": {
				"x": 232.38306227174937,
				"y": 261.2903413957752,
				"z": 236.0768505260196
			},
			"linear_velocity": {
				"x": 0.0,
				"y": 0.0,
				"z": 0.0
			},
			"angular_velocity": {
				"x": 0.0,
				"y": 0.0,
				"z": 0.0
			},
			"linear_acceleration": {
				"x": 0.0,
				"y": 0.0,
				"z": 0.0
			},
			"angular_acceleration": {
				"x": 0.0,
				"y": 0.0,
				"z": 0.0
			}
		},
		{
			"id": 5,
			"type": 2,
			"position": {
				"x": 9.227673703146305,
				"y": 15.520181101494712,
				"z": 14.36825784800702
			},
			"orientation": {
				"x": 341.6978283901586,
				"y": 124.69204254150812,
				"z": 232.66664417074796
			},
			"linear_velocity": {
				"x": 0.0,
				"y": 0.0,
				"z": 0.0
			},
			"angular_velocity": {
				"x": 0.0,
				"y": 0.0,
				"z": 0.0
			},
			"linear_acceleration": {
				"x": 0.0,
				"y": 0.0,
				"z": 0.0
			},
			"angular_acceleration": {
				"x": 0.0,
				"y": 0.0,
				"z": 0.0
			}
		},
		{
			"id": 6,
			"type": 1,
			"position": {
				"x": 5.587631623365826,
				"y": 14.160817902024979,
				"z": 6.177921457353374
			},
			"orientation": {
				"x": 356.0741296319241,
				"y": 208.6236584457131,
				"z": 282.869401564943
			},
			"linear_velocity": {
				"x": 0.0,
				"y": 0.0,
				"z": 0.0
			},
			"angular_velocity": {
				"x": 0.0,
				"y": 0.0,
				"z": 0.0
			},
			"linear_acceleration": {
				"x": 0.0,
				"y": 0.0,
				"z": 0.0
			},
			"angular_acceleration": {
				"x": 0.0,
				"y": 0.0,
				"z": 0.0
			}
		},
		{
			"id": 7,
			"type": 1,
			"position": {
				"x": 11.342980409035379,
				"y": 13.820996216632263,
				"z": 15.233647246216572
			},
			"orientation": {
				"x": 228.59785491333875,
				"y": 297.3078778119618,
				"z": 329.4564607309287
			},
			"linear_velocity": {
				"x": 0.0,
				"y": 0.0,
				"z": 0.0
			},
			"angular_velocity": {
				"x": 0.0,
				"y": 0.0,
				"z": 0.0
			},
			"linear_acceleration": {
				"x": 0.0,
				"y": 0.0,
				"z": 0.0
			},
			"angular_acceleration": {
				"x": 0.0,
				"y": 0.0,
				"z": 0.0
			}
		},
		{
			"id": 8,
			"type": 2,
			"position": {
				"x": 11.839527315955854,
				"y": 17.348028888101883,
				"z": 7.309428510827921
			},
			"orientation": {
				"x": 247.57226237445792,
				"y": 127.93130594560239,
				"z": 283.1952515359557
			},
			"linear_velocity": {
				"x": 0.0,
				"y": 0.0,
				"z": 0.0
			},
			"angular_velocity": {
				"x": 0.0,
				"y": 0.0,
				"z": 0.0
			},
			"linear_acceleration": {
				"x": 0.0,
				"y": 0.0,
				"z": 0.0
			},
			"angular_acceleration": {
				"x": 0.0,
				"y": 0.0,
				"z": 0.0
			}
		},
		{
			"id": 9,
			"type": 1,
			"position": {
				"x": 2.536970151796196,
				"y": 10.176057259532604,
				"z": 14.928726520847782
			},
			"orientation": {
				"x": 275.35593967240163,
				"y": 247.033005805257,
				"z": 361.4955071528131
			},
			"linear_velocity": {
				"x": 0.0,
				"y": 0.0,
				"z": 0.0
			},
			"angular_velocity": {
				"x": 0.0,
				"y": 0.0,
				"z": 0.0
			},
			"linear_acceleration": {
				"x": 0.0,
				"y": 0.0,
				"z": 0.0
			},
			"angular_acceleration": {
				"x": 0.0,
				"y": 0.0,
				"z": 0.0
			}
		}
	],
	"timestamp": 22125
}